orchcli/__init__.py
orchcli/main.py
orchcli/templates/__init__.py
orchcli/templates/secrets/__init__.py
orchcli/templates/secrets/anthropic.json
orchcli/templates/secrets/gemini.json
orchcli/templates/secrets/ollama.json
orchcli/templates/secrets/openai.json
orchcli/templates/secrets/openai_compatible.json
orchcli/templates/secrets/tavily.json
orchagent_cli-0.1.5.dist-info/METADATA
orchagent_cli-0.1.5.dist-info/WHEEL
orchagent_cli-0.1.5.dist-info/entry_points.txt
orchagent_cli-0.1.5.dist-info/top_level.txt
orchagent_cli-0.1.5.dist-info/RECORD
