Metadata-Version: 2.4
Name: orchagent-cli
Version: 0.1.5
Summary: CLI for the Orchagent API
Author-email: Orchagent <dev@example.com>
Project-URL: Homepage, https://github.com/eladrave/orchagent-cli
Requires-Python: >=3.10
Requires-Dist: typer[all]>=0.12
Requires-Dist: rich>=13.0
Requires-Dist: orchagent>=0.1.3
